NLPSimplified/__init__.py
NLPSimplified/pipeline.py
NLPSimplified-1.0.3.dist-info/LICENSE
NLPSimplified-1.0.3.dist-info/METADATA
NLPSimplified-1.0.3.dist-info/WHEEL
NLPSimplified-1.0.3.dist-info/top_level.txt
NLPSimplified-1.0.3.dist-info/RECORD
