Metadata-Version: 2.1
Name: NLPSimplified
Version: 1.0.3
Summary: A simple NLP pipeline using spaCy
Home-page: UNKNOWN
Author: Avneh Singh Bhatia
Author-email: avnehb@gmail.com
License: UNKNOWN
Platform: UNKNOWN
License-File: LICENSE
Requires-Dist: spacy (<4.0.0,>=3.0.0)
